{
    "Crosshair": "准星",
    "Ivorfall": "艾沃福尔",
    "Circus": "马戏团",
    "Electrique": "电气",
    "Cryptmaster": "地牢大师",
    "RESIST": "抵抗",
    "World": "世界",
    "War": "战争",
    "Battle": "战斗",
    "Fantasy": "幻想",
    "RPG": "角色扮演",
    "Simulator": "模拟器",
    "Adventure": "冒险",
    "Strategy": "策略",
    "Action": "动作",
    "Horror": "恐怖",
    "Puzzle": "解谜",
    "Racing": "竞速",
    "Sports": "体育",
    "Shooter": "射击",
    "Survival": "生存",
    "Building": "建造",
    "Online": "在线",
    "Multiplayer": "多人",
    "Singleplayer": "单人",
    "Free": "免费",
    "Demo": "试玩",
    "VR": "虚拟现实",
    "MMO": "大型多人在线",
    "RTS": "即时战略",
    "FPS": "第一人称射击",
    "TPS": "第三人称射击",
    "MOBA": "多人在线战术竞技"
}